papass/__init__.py
papass/__main__.py
papass/alphabet.py
papass/commands.py
papass/passphrase_generator.py
papass/password_generator.py
papass/py.typed
papass/utils.py
papass/wordlist.py
papass/random_source/__init__.py
papass/random_source/base.py
papass/random_source/dice.py
papass/random_source/registry.py
papass/random_source/system.py
papass-0.1.0.dist-info/entry_points.txt
papass-0.1.0.dist-info/LICENSE
papass-0.1.0.dist-info/WHEEL
papass-0.1.0.dist-info/METADATA
papass-0.1.0.dist-info/RECORD
