Metadata-Version: 2.1
Name: papass
Version: 0.1.0
Summary: papass is a simple library to generate passphrases and passwords.
Author: Reinhard Stahn
Requires-Python: >= 3.10
Classifier: License :: OSI Approved :: MIT License
Requires-Dist: click
Requires-Dist: hypothesis ; extra == "dev"
Requires-Dist: mypy ; extra == "dev"
Requires-Dist: pytest ; extra == "dev"
Requires-Dist: pytest-timeout ; extra == "dev"
Requires-Dist: ruff ; extra == "dev"
Requires-Dist: python-lsp-server ; extra == "dev-pylsp"
Requires-Dist: python-lsp-ruff ; extra == "dev-pylsp"
Requires-Dist: pylsp-mypy ; extra == "dev-pylsp"
Requires-Dist: pylsp-rope ; extra == "dev-pylsp"
Requires-Dist: myst-parser ; extra == "docs"
Requires-Dist: sphinx ; extra == "docs"
Requires-Dist: sphinx-book-theme ; extra == "docs"
Project-URL: documentation, https://papass.readthedocs.io
Project-URL: source, https://github.com/rainij/papass
Provides-Extra: dev
Provides-Extra: dev-pylsp
Provides-Extra: docs
